better_cryptography/__init__.py
better_cryptography/ciphers.py
better_cryptography/diagonostic.py
better_cryptography/file_encryption.cpython-39-x86_64-linux-gnu.so
better_cryptography/log.py
better_cryptography/setup.py
better_cryptography/util.py
better_cryptography-1.0.1.dist-info/METADATA
better_cryptography-1.0.1.dist-info/WHEEL
better_cryptography-1.0.1.dist-info/top_level.txt
better_cryptography-1.0.1.dist-info/RECORD
