Metadata-Version: 2.1
Name: better-cryptography
Version: 1.0.1
Summary: A module for encryption and information security operations.
Home-page: UNKNOWN
Author: Wyatt Garrioch
Author-email: w.garrioch456@gmail.com
License: UNKNOWN
Keywords: python,encryption,AES,ciphers,encryption alogorithms,information security
Platform: UNKNOWN
Classifier: Development Status :: 3 - Alpha
Classifier: Intended Audience :: Education
Classifier: Programming Language :: Python :: 3
Classifier: Operating System :: OS Independent
Classifier: License :: OSI Approved :: MIT License
Requires-Dist: cryptography
Requires-Dist: pycryptodome
Requires-Dist: rsa
